nnkurlparser/__init__.py
nnkurlparser/nnkurlparser.py
nnkurlparser-0.3.dist-info/LICENSE.txt
nnkurlparser-0.3.dist-info/METADATA
nnkurlparser-0.3.dist-info/WHEEL
nnkurlparser-0.3.dist-info/entry_points.txt
nnkurlparser-0.3.dist-info/top_level.txt
nnkurlparser-0.3.dist-info/RECORD
