Metadata-Version: 2.1
Name: nnkurlparser
Version: 0.3
Home-page: https://github.com/Rnaveennithyakalyan/nnkurlparser
Author: R. NAVEEN NITHYA KALYAN
Author-email: naveennithyakalyan@gmail.com
Classifier: License :: OSI Approved :: MIT License
License-File: LICENSE.txt
